seibpy/__init__.py
seibpy/_modidx.py
seibpy/core.py
seibpy-0.0.1.dist-info/licenses/LICENSE
seibpy-0.0.1.dist-info/METADATA
seibpy-0.0.1.dist-info/WHEEL
seibpy-0.0.1.dist-info/entry_points.txt
seibpy-0.0.1.dist-info/top_level.txt
seibpy-0.0.1.dist-info/RECORD
